heart_model/VERSION
heart_model/__init__.py
heart_model/config.yml
heart_model/pipeline.py
heart_model/predict.py
heart_model/train_pipeline.py
heart_model/config/__init__.py
heart_model/config/core.py
heart_model/datasets/__init__.py
heart_model/datasets/test.csv
heart_model/datasets/train.csv
heart_model/processing/__init__.py
heart_model/processing/data_manager.py
heart_model/processing/features.py
heart_model/processing/validation.py
heart_model/trained_models/__init__.py
heart_model/trained_models/heart_model_output_v0.0.11.pkl
heart_model-0.0.11.dist-info/METADATA
heart_model-0.0.11.dist-info/WHEEL
heart_model-0.0.11.dist-info/top_level.txt
heart_model-0.0.11.dist-info/RECORD
