Metadata-Version: 2.1
Name: heart-model
Version: 0.0.11
Summary: Heart decease model package.
Home-page: https://github.com/Ra7777/heart_model
Author: Rashid Meylanov
Author-email: rashmeilll@gmail.com
License: BSD-3
Classifier: License :: OSI Approved :: MIT License
Classifier: Programming Language :: Python
Classifier: Programming Language :: Python :: 3
Classifier: Programming Language :: Python :: 3.10
Classifier: Programming Language :: Python :: Implementation :: CPython
Classifier: Programming Language :: Python :: Implementation :: PyPy
Requires-Python: >=3.10.0
Requires-Dist: feature-engine (<1.1.0,>=1.0.2)
Requires-Dist: joblib (>=1.1.1)
Requires-Dist: numpy (<1.24.0,>=1.23.5)
Requires-Dist: pandas (<1.6.0,>=1.5.3)
Requires-Dist: pydantic (<1.11,>=1.10)
Requires-Dist: ruamel.yaml (==0.16.12)
Requires-Dist: scikit-learn (>=1.2.2)
Requires-Dist: strictyaml (<1.4.0,>=1.3.2)
